<?xml version='1.0' encoding='UTF-8'?>
<JCSGMLInputTemplate>
<CollectionElement>osgb:FeatureCollection</CollectionElement>
<FeatureElement>osgb:CartographicText</FeatureElement>
<GeometryElement>osgb:anchorPoint</GeometryElement>
<ColumnDefinitions>
<column>
<name>Toid</name>
<type>STRING</type>
<valueelement elementname='osgb:CartographicText'/>
<valuelocation position='attribute' attributeName='fid'/>
</column>
<column>
<name>featureCode</name>
<type>STRING</type>
<valueelement elementname='osgb:featureCode'/>
<valuelocation position='body'/>
</column>
<column>
<name>version</name>
<type>INTEGER</type>
<valueelement elementname='osgb:version'/>
<valuelocation position='body'/>
</column>
<column>
<name>versionDate</name>
<type>DATE</type>
<valueelement elementname='osgb:versionDate'/>
<valuelocation position='body'/>
</column>
<column>
<name>Theme</name>
<type>OBJECT</type>
<valueelement elementname='osgb:theme'/>
<valuelocation position='body'/>
</column>
<column>
<name>changeHistory</name>
<type>OBJECT</type>
<valueelement elementname='osgb:changeHistory'/>
<valuelocation position='body'/>
</column>
<column>
<name>DescriptiveGroup</name>
<type>OBJECT</type>
<valueelement elementname='osgb:descriptiveGroup'/>
<valuelocation position='body'/>
</column>
<column>
<name>descriptiveTerm</name>
<type>OBJECT</type>
<valueelement elementname='osgb:descriptiveTerm'/>
<valuelocation position='body'/>
</column>
<column>
<name>make</name>
<type>STRING</type>
<valueelement elementname='osgb:make'/>
<valuelocation position='body'/>
</column>
<column>
<name>physicalLevel</name>
<type>INTEGER</type>
<valueelement elementname='osgb:physicalLevel'/>
<valuelocation position='body'/>
</column>
<column>
<name>physicalPresence</name>
<type>STRING</type>
<valueelement elementname='osgb:physicalPresence'/>
<valuelocation position='body'/>
</column>
<column>
<name>textRendering</name>
<type>OBJECT</type>
<valueelement elementname='osgb:textRendering'/>
<valuelocation position='body'/>
</column>
<column>
<name>textString</name>
<type>STRING</type>
<valueelement elementname='osgb:textString'/>
<valuelocation position='body'/>
</column>
</ColumnDefinitions>
</JCSGMLInputTemplate>